quqie/__init__.py
quqie/cli.py
quqie/core/__init__.py
quqie/exceptions.py
quqie/settings/__init__.py
quqie/spiders/__init__.py
quqie/utils/__init__.py
quqie/web/__init__.py
quqie-0.0.2.dist-info/WHEEL
quqie-0.0.2.dist-info/LICENSE
quqie-0.0.2.dist-info/METADATA
quqie-0.0.2.dist-info/entry_points.txt
quqie-0.0.2.dist-info/RECORD
